cirque/__init__.py
cirque/_version.py
cirque/ad5672_5684.py
cirque/ad7291.py
cirque/balunatten.py
cirque/bidirectionalmixer.py
cirque/capreadoutchain.py
cirque/chip_info.py
cirque/detector_emulator.py
cirque/dmacontroller.py
cirque/eventdetection.py
cirque/fluxrampdemod.py
cirque/fluxrampgenerator.py
cirque/lmk04208.py
cirque/lmx2594.py
cirque/ltc2000_cfg.py
cirque/ltc5586.py
cirque/memmap.py
cirque/multichannelddc.py
cirque/pimc.py
cirque/pp_channelizer.py
cirque/rampgen.py
cirque/rfdc.py
cirque/rfpcb.py
cirque/servicehubcontrol.py
cirque/servicehubutils.py
cirque/signalamplifier.py
cirque/stimulation.py
cirque/sysmon.py
cirque/tdmchannelmultipick.py
cirque/vna.py
cirque/deprecated/dma.py
cirque/packages/grpc/.gitkeep
cirque/packages/grpc/ad5672_5684_pb2.py
cirque/packages/grpc/ad5672_5684_pb2.pyi
cirque/packages/grpc/ad5672_5684_pb2_grpc.py
cirque/packages/grpc/ad5675_pb2.py
cirque/packages/grpc/ad5675_pb2.pyi
cirque/packages/grpc/ad5675_pb2_grpc.py
cirque/packages/grpc/ad7291_pb2.py
cirque/packages/grpc/ad7291_pb2.pyi
cirque/packages/grpc/ad7291_pb2_grpc.py
cirque/packages/grpc/bench_pb2.py
cirque/packages/grpc/bench_pb2.pyi
cirque/packages/grpc/bench_pb2_grpc.py
cirque/packages/grpc/bidirectionalmixer_pb2.py
cirque/packages/grpc/bidirectionalmixer_pb2.pyi
cirque/packages/grpc/bidirectionalmixer_pb2_grpc.py
cirque/packages/grpc/capreadoutchain_pb2.py
cirque/packages/grpc/capreadoutchain_pb2.pyi
cirque/packages/grpc/capreadoutchain_pb2_grpc.py
cirque/packages/grpc/chip_info_pb2.py
cirque/packages/grpc/chip_info_pb2.pyi
cirque/packages/grpc/chip_info_pb2_grpc.py
cirque/packages/grpc/datatypes_pb2.py
cirque/packages/grpc/datatypes_pb2.pyi
cirque/packages/grpc/datatypes_pb2_grpc.py
cirque/packages/grpc/detector_emulator_pb2.py
cirque/packages/grpc/detector_emulator_pb2.pyi
cirque/packages/grpc/detector_emulator_pb2_grpc.py
cirque/packages/grpc/digital_trigger_pb2.py
cirque/packages/grpc/digital_trigger_pb2.pyi
cirque/packages/grpc/digital_trigger_pb2_grpc.py
cirque-1.0.dist-info/METADATA
cirque-1.0.dist-info/WHEEL
cirque-1.0.dist-info/licenses/COPYING
cirque-1.0.dist-info/RECORD
