Metadata-Version: 2.4
Name: cirque
Version: 1.0
Summary: Python client for the communication with the SDR platform. The client consists of the api to the individual modules on the platform and generates the grpc files. Additionally, some utility files for postprocessing are part of this program.
Project-URL: Repository, https://gitlab.kit.edu/kit/ipe-sdr/open_source/cirque
Author-email: Quantum Interface <quantuminterface@ipe.kit.edu>
License-File: COPYING
Classifier: Development Status :: 3 - Alpha
Classifier: License :: OSI Approved :: GNU General Public License v3 or later (GPLv3+)
Classifier: Operating System :: OS Independent
Classifier: Programming Language :: Python :: 3
Classifier: Programming Language :: Python :: 3.9
Requires-Python: >=3.9
Requires-Dist: bitarray>=3.4.3
Requires-Dist: grpcio==1.73.1
Requires-Dist: matplotlib>=3.7
Requires-Dist: numpy>=1.24
Requires-Dist: protobuf==6.31.1
Requires-Dist: scipy>=1.10
Requires-Dist: tqdm>=4.67.1
Requires-Dist: typing-extensions>=4.14.0
Requires-Dist: wrapt>=1.16
Requires-Dist: zerorpc>=0.6.3
